lcdp_postgres_utils/__init__.py
lcdp_postgres_utils/executor_factory.py
lcdp_postgres_utils/executors/__init__.py
lcdp_postgres_utils/executors/executor13.py
lcdp_postgres_utils/executors/executor14.py
lcdp_postgres_utils/executors/executor16.py
lcdp_postgres_utils/restricted_user.py
lcdp_postgres_utils/user.py
lcdp_postgres_utils/utils/__init__.py
lcdp_postgres_utils/utils/postgres.py
lcdp_postgres_utils/utils/ssm.py
lcdp_postgres_utils-1.5.9.dist-info/METADATA
lcdp_postgres_utils-1.5.9.dist-info/WHEEL
lcdp_postgres_utils-1.5.9.dist-info/RECORD
